{
    "id": "LateRoomsConversion",
    "name": "LateRooms.com Conversion",
    "components": [
        {
          "type": "SharedDataStore",
          "title": "LateRooms Conversion",
          "storeId": "BookingData",
          "dataSource": "elasticsearch",
          "host": "http://logs.laterooms.com:9200",
          "timeProperties": [
            "query.filtered.filter.bool.must.0.range.@timestamp",
            "aggs.bookingsbytime.date_histogram.extended_bounds"
          ],
          "filters": [
            { 
              "id": "device",
              "title": "Device",
              "options": {
                "All": "",
                "Internet Explorer": { "browser": "ie" },
                "Chrome": { "browser": "chrome" },
                "Firefox": { "browser": "firefox" },
                "Safari (Desktop)": { "browser": "safari", "device": "other" },
                "Safari (iPad)": { "browser": "safari", "device": "ipad" },
                "Safari (iPhone)": { "browser": "safari", "device": "iphone" },
                "Android": { "browser": "android" }
              },
              "allowMultiple": false,
              "setOnProperties": {
                "browser": "query.query.filtered.filter.bool.must.#.term.user|userAgent|name",
                "device": "query.query.filtered.filter.bool.must.#.term.user|userAgent|device" 
              }
            }
          ],
          "defaultTimeFrame": {
            "timeFrame": 0,
            "units": "daysAgo"
          },
          "queries": {
            "modifiers": {
              "today": { },
              "lastWeek": { "timeOffset": { "weeks": -1 } },
              "2weeksago": { "timeOffset": { "weeks": -2 } },
              "3weeksago": { "timeOffset": { "weeks": -3 } }
            },
            "query": {
              "query": {
                "filtered": {
                  "filter": {
                    "bool": {
                      "must": [
                        {
                          "range" : {
                            "@timestamp" : { }
                          }
                        },
                        {
                          "term" : {
                            "type" : "session"
                          }
                        },
                        {
                          "term": {
                            "user.type": "human"
                          }
                        }
                      ]
                    }
                  }
                }
              },
              "aggs": {
                "bookingsbytime" : {
                  "date_histogram" : {
                      "min_doc_count": 0,
                      "field" : "@timestamp",
                      "interval" : "1h",
                      "extended_bounds": {}
                  },
                  "aggs": {
                    "bookings": {
                      "filter": {
                        "term": {
                          "booked": "true"
                        }
                      }
                    }
                  }
                }
              },
              "size": 0
            }
          },
          "mappings": [
            { 
              "type": "extractFromDateHistogram",
              "aggregateName": "bookingsbytime",
              "fields": {
                "bookings": "bookings.doc_count",
                "sessions": "doc_count"
              }
            },
            { 
              "type": "calculation",
              "calculation": "percentage",
              "by": { "field": "bookings", "over": "sessions" },
              "toField": "commission"
            },
            {
              "type": "stats",
              "fields": ["lastWeek", "2weeksago", "3weeksago"],
              "stds": [1, 2],
              "property": "commission"
            },
            {
              "type": "confidenceInterval",
              "confidenceLevel": "90%"
            }
          ]
        },
        {
          "type": "LineGraphAndCounter",
          "title": "Conversion",
          "summaryText": "Conversion tracking for LateRooms.com (WEB)",
          "storeId": "BookingData",
          "counter": {
              "precision": 0,
              "counters": [
                { "id": "today", "color": "purple", "value": "today", "text": "Today" },
                { "id": "average", "color": "green", "value": "average", "text": "Average" }
              ],
              "window": {
                "skip": 0,
                "take": 0
              }
          },
          "graph": {
              "className": "commission-graph",
              "lines": [
                { "id": "today", "color": "purple", "value": "today.commission" },
                { "id": "mean", "color": "green", "value": "value.mean" }
              ],
              "areas": [
                { "id": "plusTwoStd", "color": "#AAA", "start": "value.standardDeviations.2.minus", "end": "value.standardDeviations.2.plus" },
                { "id": "plusOneStd", "color": "#CCC", "start": "value.standardDeviations.1.minus", "end": "value.standardDeviations.1.plus" }
              ]
          }
        },
        {
          "type": "LineGraphAndCounter",
          "title": "Conversion",
          "summaryText": "Conversion tracking for LateRooms.com (WEB)",
          "storeId": "BookingData",
          "counter": {
              "counters": [
                { "id": "b-counter-today", "color": "purple", "text": "Today" },
                { "id": "b-counter-lastWeek", "color": "#0C5046", "text": "Last Week" },
                { "id": "b-counter-2weeksago", "color": "#01CFB0", "text": "2 Weeks Ago" },
                { "id": "b-counter-3weeksago", "color": "#907616", "text": "3 Weeks Ago" }
              ]
          },
          "graph": {
              "className": "commission-graph",
              "lines": [
                { "id": "b-today", "color": "purple", "value": "today.commission" },
                { "id": "b-lastWeek", "color": "#0C5046", "value": "lastWeek.commission" },
                { "id": "b-2weeksago", "color": "#01CFB0", "value": "2weeksago.commission" },
                { "id": "b-3weeksago", "color": "#907616", "value": "3weeksago.commission" }
              ]
          }
        }
    ]
}
